README
setup.py
htmlcolor/__init__.py
htmlcolor/generate_names.py
htmlcolor/names.py
htmlcolor/parser.py
htmlcolor.egg-info/PKG-INFO
htmlcolor.egg-info/SOURCES.txt
htmlcolor.egg-info/dependency_links.txt
htmlcolor.egg-info/top_level.txt