Metadata-Version: 1.0
Name: htmlcolor
Version: 0.1
Summary: Parsing HTML and CSS color values
Home-page: http://github.com/ext/pyhtmlcolor
Author: David Sveningsson
Author-email: ext@sidvind.com
License: BSD
Keywords: color html css
Platform: UNKNOWN
